equinix/__init__.py
equinix/services/__init__.py
equinix/services/fabricv4/__init__.py
equinix/services/fabricv4/api_client.py
equinix/services/fabricv4/api_response.py
equinix/services/fabricv4/configuration.py
equinix/services/fabricv4/exceptions.py
equinix/services/fabricv4/rest.py
equinix/services/fabricv4/api/__init__.py
equinix/services/fabricv4/api/cloud_events_api.py
equinix/services/fabricv4/api/cloud_routers_api.py
equinix/services/fabricv4/api/connections_api.py
equinix/services/fabricv4/api/health_api.py
equinix/services/fabricv4/api/marketplace_subscriptions_api.py
equinix/services/fabricv4/api/metrics_api.py
equinix/services/fabricv4/api/metros_api.py
equinix/services/fabricv4/api/networks_api.py
equinix/services/fabricv4/api/port_packages_api.py
equinix/services/fabricv4/api/ports_api.py
equinix/services/fabricv4/api/precision_time_api.py
equinix/services/fabricv4/api/prices_api.py
equinix/services/fabricv4/api/route_aggregation_rules_api.py
equinix/services/fabricv4/api/route_aggregations_api.py
equinix/services/fabricv4/api/route_filter_rules_api.py
equinix/services/fabricv4/api/route_filters_api.py
equinix/services/fabricv4/api/routing_protocols_api.py
equinix/services/fabricv4/api/service_profiles_api.py
equinix/services/fabricv4/api/service_tokens_api.py
equinix/services/fabricv4/api/statistics_api.py
equinix/services/fabricv4/api/stream_alert_rules_api.py
equinix/services/fabricv4/api/stream_subscriptions_api.py
equinix/services/fabricv4/api/streams_api.py
equinix/services/fabricv4/models/__init__.py
equinix/services/fabricv4/models/access_point.py
equinix/services/fabricv4/models/access_point_role.py
equinix/services/fabricv4/models/access_point_selector.py
equinix/services/fabricv4/models/access_point_selector_type.py
equinix/services/fabricv4/models/access_point_type.py
equinix/services/fabricv4/models/actions.py
equinix/services/fabricv4/models/add_operation.py
equinix/services/fabricv4/models/alert_rule_post_request.py
equinix-0.14.0.dist-info/licenses/LICENSE
equinix-0.14.0.dist-info/METADATA
equinix-0.14.0.dist-info/WHEEL
equinix-0.14.0.dist-info/top_level.txt
equinix-0.14.0.dist-info/RECORD
