Metadata-Version: 2.4
Name: equinix
Version: 0.14.0
Summary: Equinix SDK for Python
Home-page: https://github.com/equinix/equinix-sdk-python
Author: Equinix
License: MIT
Keywords: Equinix
Requires-Python: >=3.7
License-File: LICENSE
Requires-Dist: urllib3<3.0.0,>=2.2.2
Requires-Dist: python-dateutil
Requires-Dist: pydantic>=2
Requires-Dist: typing-extensions>=4.7.1
Dynamic: author
Dynamic: description
Dynamic: description-content-type
Dynamic: home-page
Dynamic: keywords
Dynamic: license
Dynamic: license-file
Dynamic: requires-dist
Dynamic: requires-python
Dynamic: summary
